teacher/__init__.py
teacher/datasets/__init__.py
teacher/datasets/_base.py
teacher/datasets/data/FLAVIA3.csv
teacher/datasets/data/adult.csv
teacher/datasets/data/basket.csv
teacher/datasets/data/beer.csv
teacher/datasets/data/breast.csv
teacher/datasets/data/compas-scores-two-years.csv
teacher/datasets/data/german_credit.csv
teacher/datasets/data/heloc_dataset_v1.csv
teacher/datasets/data/phishing.csv
teacher/datasets/data/pima-indians-diabetes.csv
teacher/datasets/data/small_basket.csv
teacher/datasets/tests/__init__.py
teacher/datasets/tests/test_base.py
teacher/explanation/FBDT_explainer.py
teacher/explanation/FDT_explainer.py
teacher/explanation/FID3_explainer.py
teacher/explanation/__init__.py
teacher/explanation/_base_explainer.py
teacher/explanation/_counterfactual.py
teacher/explanation/_factual.py
teacher/explanation/_factual_local_explainer.py
teacher/explanation/tests/__init__.py
teacher/explanation/tests/conftest.py
teacher/explanation/tests/test_counterfactual.py
teacher/explanation/tests/test_explainer.py
teacher/explanation/tests/test_factual.py
teacher/fuzzy/__init__.py
teacher/fuzzy/_base.py
teacher/fuzzy/_discretize.py
teacher/fuzzy/fuzzy_set.py
teacher/fuzzy/fuzzy_variable.py
teacher/fuzzy/tests/__init__.py
teacher/fuzzy/tests/test_base.py
teacher/fuzzy/tests/test_fuzzy_set.py
teacher/metrics/__init__.py
teacher/metrics/_counterfactual.py
teacher/metrics/_rule.py
teacher/metrics/tests/__init__.py
teacher/metrics/tests/test_rule.py
teacher/neighbors/__init__.py
teacher/neighbors/_base_neighborhood.py
teacher/neighbors/_exceptions.py
teacher/neighbors/_fuzzy_neighborhood.py
teacher/neighbors/_lore_neighborhood.py
teacher/neighbors/_sampling_neighborhood.py
teacher/neighbors/_simple_neighborhood.py
teacher/neighbors/genetic_algorithm.py
teacher/neighbors/gpdatagenerator.py
teacher/neighbors/neighbor_generator.py
teacher/neighbors/tests/__init__.py
teacher/neighbors/tests/test_genetic_algorithm.py
teacher/neighbors/tests/test_neigborhoods.py
teacher_xai-1.0.1.dist-info/LICENSE
teacher_xai-1.0.1.dist-info/METADATA
teacher_xai-1.0.1.dist-info/WHEEL
teacher_xai-1.0.1.dist-info/top_level.txt
teacher_xai-1.0.1.dist-info/RECORD
