Metadata-Version: 2.1
Name: teacher-xai
Version: 1.0.1
Summary: Package for Machine Learning explanation in Python.
Author-email: Guillermo Tomás Fernández Martin <Guillermo.Fernandez@uclm.es>
Maintainer-email: Guillermo Tomás Fernández Martin <Guillermo.Fernandez@uclm.es>
License: MIT License
Project-URL: Homepage, https://xai-teacher.readthedocs.io/en/latest/
Project-URL: Documentation, https://xai-teacher.readthedocs.io/en/latest/
Project-URL: Repository, https://github.com/Kaysera/teacher
Requires-Python: >=3.9
License-File: LICENSE
Requires-Dist: numpy >=1.19.3
Requires-Dist: pandas
Requires-Dist: scikit-learn
Requires-Dist: deap
Requires-Dist: imblearn
Requires-Dist: matplotlib
